public class io/github/lukebemish/lesslazyitems/ItemWandDispenserBehavior extends net/minecraft/core/dispenser/DefaultDispenseItemBehavior {

    private final persistent Z

    public <init>(Z)V {
        aload 0
        invokespecial net/minecraft/core/dispenser/DefaultDispenseItemBehavior.<init>()V
        aload 0
        iload 1
        putfield io/github/lukebemish/lesslazyitems/ItemWandDispenserBehavior.persistent Z
        return
    }

    public execute(net/minecraft/core/BlockSource,net/minecraft/world/item/ItemStack)net/minecraft/world/item/ItemStack {
        aload 1
        invokeinterface net/minecraft/core/BlockSource.getLevel()net/minecraft/server/level/ServerLevel
        aload 1
        invokeinterface net/minecraft/core/BlockSource.getPos()net/minecraft/core/BlockPos
        aload 1
        invokeinterface net/minecraft/core/BlockSource.getBlockState()net/minecraft/world/level/block/state/BlockState
        getstatic net/minecraft/world/level/block/DispenserBlock.FACING net/minecraft/world/level/block/state/properties/DirectionProperty
        invokevirtual net/minecraft/world/level/block/state/BlockState.getValue(net/minecraft/world/level/block/state/properties/Property)java/lang/Comparable
        checkcast net/minecraft/core/Direction
        iconst 4
        invokevirtual net/minecraft/core/BlockPos.relative(net/minecraft/core/Direction,I)net/minecraft/core/BlockPos
        aload 0
        getfield io/github/lukebemish/lesslazyitems/ItemWandDispenserBehavior.persistent Z
        invokestatic io/github/lukebemish/lesslazyitems/ItemWandItem.convertNearbyItems(net/minecraft/world/level/Level,net/minecraft/core/BlockPos,Z)V

        aload 2
        areturn
    }
}